clarifaipyspark/__init__.py
clarifaipyspark/client.py
clarifaipyspark/dataset.py
clarifai_pyspark-0.0.4.dist-info/LICENSE
clarifai_pyspark-0.0.4.dist-info/METADATA
clarifai_pyspark-0.0.4.dist-info/WHEEL
clarifai_pyspark-0.0.4.dist-info/top_level.txt
clarifai_pyspark-0.0.4.dist-info/RECORD
