Metadata-Version: 2.1
Name: clarifai-pyspark
Version: 0.0.4
Summary: Clarifai PySpark Python SDK
Home-page: https://github.com/Clarifai/clarifai-pyspark
Author: Clarifai
Author-email: support@clarifai.com
License: Apache 2.0
Classifier: Topic :: Scientific/Engineering :: Artificial Intelligence
Classifier: Programming Language :: Python :: 3
Classifier: License :: OSI Approved :: Apache Software License
Classifier: Operating System :: OS Independent
Requires-Python: >=3.8
License-File: LICENSE
Requires-Dist: clarifai ==10.0.1
Requires-Dist: pyspark ==3.5.0
